Metadata-Version: 1.1
Name: maoud
Version: 0.1.dev0
Summary: Simulating generalized fading channels
Home-page: https://github.com/mirca/maoud
Author: mirca
Author-email: jvmirca@gmail.com
License: MIT
Keywords: statistics probability
Platform: UNKNOWN
Classifier: Development Status :: 3 - Alpha
Classifier: Intended Audience :: Science/Research
Classifier: License :: OSI Approved :: MIT License
Classifier: Programming Language :: Python :: 3.6
